chapagol/__init__.py
chapagol/cli.py
chapagol/set_up.py
uv_project-0.2.0.dist-info/METADATA
uv_project-0.2.0.dist-info/WHEEL
uv_project-0.2.0.dist-info/entry_points.txt
uv_project-0.2.0.dist-info/top_level.txt
uv_project-0.2.0.dist-info/RECORD
