Metadata-Version: 2.1
Name: uv-project
Version: 0.2.0
Summary: Add your description here
Requires-Python: >=3.13
Requires-Dist: typer>=0.15.1
